lexd/__init__.py
lexd/main.py
lexd-1.0.0.data/scripts/main.py
lexd-1.0.0.dist-info/LICENSE
lexd-1.0.0.dist-info/METADATA
lexd-1.0.0.dist-info/WHEEL
lexd-1.0.0.dist-info/top_level.txt
lexd-1.0.0.dist-info/RECORD
