Metadata-Version: 2.1
Name: lexd
Version: 1.0.0
Summary: Ma librairie de fonctions utiles
Home-page: https://github.com/importFourmi/lexd
Author: importFourmi
Author-email: calvin.galagain@gmail.com
Classifier: Programming Language :: Python :: 3
License-File: LICENSE
Requires-Dist: opencv-python
Requires-Dist: mediapipe
Requires-Dist: numpy
